{"1": "금속 잔해를 투척해 <dmg elem=\"physics\" />를 줍니다.\n<sec typ=\"cond\">적중 시</sec>, 대상의 <sec typ=\"buff\"><buff typ=\"AP_DOWN\" /> AP <val idx=\"0\" /></sec>이(가) 감소하고 <sec typ=\"buff\"><buff typ=\"REMOVE_BUFF\" /> 받는 피해 감소 효과를 해제</sec>합니다.\n<sec typ=\"cond\">치명타 시</sec>, 2라운드 동안 대상이 <sec typ=\"buff\"><buff typ=\"VULNERABLE\" /> 받는 피해 <val idx=\"4\" r /></sec>가 증가하고 자신은 <sec typ=\"buff\"><sec typ=\"note\">잔해</sec>를 1중첩 획득</sec>합니다.", "2": "금속으로 된 감옥에 적을 가두어 <sec typ=\"attr\">보호 무시</sec> <dmg elem=\"physics\" />를 줍니다.\n<sec typ=\"cond\">적중 시</sec>, 2라운드 동안 대상은 <sec typ=\"buff\"><buff typ=\"EVADE_DOWN\" /> 회피 <val idx=\"0\" r /></sec>가 감소하고 <sec typ=\"buff\"><buff typ=\"SNARE\" /> 이동 불가</sec> 상태가 됩니다.\n<sec typ=\"cond\">스킬 사용 후</sec> <sec typ=\"buff\"><sec typ=\"note\">잔해</sec>를 모두 소모</sec>하며, 소모한 <sec typ=\"note\">잔해</sec> 중첩 수에 따라 다음 효과가 추가로 적용됩니다.\n<box t=\"잔해 1중첩\"><sec typ=\"buff\"><buff typ=\"RANGE_DOWN\" /> 사거리 <val idx=\"5\" /></sec> 감소</box>\n<box t=\"잔해 2중첩\"><sec typ=\"buff\"><buff typ=\"AP_DOWN\" /> 행동력 <val idx=\"6\" r /></sec> 감소</box>\n<box t=\"잔해 3중첩\"><sec typ=\"buff\"><buff typ=\"REMOVE_BUFF\" /> 강화 효과 해제</sec></box>", "3": "<sec typ=\"cond\">라운드 개시 시</sec>, 범위 내 아군의 <sec typ=\"buff\"><buff typ=\"DAMAGE_REDUCE\" /> 받는 피해 <val idx=\"4\" r inv /></sec>가 감소하고 <sec typ=\"buff\"><buff typ=\"FIRERES_UP\" /><buff typ=\"ICERES_UP\" /><buff typ=\"LIGHTNINGRES_UP\" /> 모든 속성 저항 <val idx=\"5\" r /></sec>가 증가합니다.\n<sec typ=\"cond\">대상의 HP가 50% 이상인 경우</sec>, 상기 효과 수치가 50% 증폭됩니다.\n<sec typ=\"cond\">라운드 개시 시</sec> <sec typ=\"cond\">자신의 HP가 50% 이상인 경우</sec>, 범위 내 아군 보호기는 추가로 <sec typ=\"buff\"><buff typ=\"DEF_UP\" /> 방어력 <val idx=\"12\" r /></sec> / <sec typ=\"buff\"><buff typ=\"AP_UP\" /> AP <val idx=\"13\" /></sec>이(가) 증가합니다.\n<sec typ=\"cond\">상기 효과를 보유한 아군이 있을 경우</sec>, 자신도 동일한 효과를 획득합니다.", "4": "<sec typ=\"cond\">라운드 개시 시</sec>, 자신은 <sec typ=\"buff\"><buff typ=\"DAMAGE_ABSORB\" /> 방어막 <val idx=\"2\" signless /></sec>을(를) 획득합니다.\n<sec typ=\"cond\">공격 받을 시</sec> <sec typ=\"cond\">자신에게 방어막이 없을 경우</sec>, 범위 내 아군에게 1라운드 동안 <sec typ=\"buff\"><buff typ=\"DAMAGE_ABSORB\" /> 방어막 <val idx=\"4\" signless /></sec>을(를) 부여합니다.\n<sec typ=\"cond\"><sec typ=\"note\">잔해</sec>를 보유한 경우</sec>, <sec typ=\"note\">반응 방벽</sec>으로 인한 <sec typ=\"buff\"><buff typ=\"DAMAGE_ABSORB\" /> 방어막</sec>이 두 배로 증폭됩니다.\n<sec>자신의 액티브 스킬은 레벨당 20%의 적중 보정이 적용됩니다.</sec>", "5": "<sec typ=\"cond\">대기</sec> 또는 <sec typ=\"cond\">적 사망 시</sec>, 주변의 금속 잔해를 수집하여 자신의 <sec typ=\"buff\"><buff typ=\"DEF_UP\" /> 방어력 <val idx=\"0\" /></sec>이(가) 증가합니다. <sec>(최대 3중첩)</sec>\n<sec typ=\"cond\">라운드 개시 시</sec>, <sec typ=\"note\">잔해</sec> 1 중첩당 범위 내 아군 보호기의 <sec typ=\"dmg\"><buff typ=\"SKILL_UP\" /> 방어력 <val idx=\"6\" r />만큼 스킬 위력</sec>이 증가합니다.\n<sec typ=\"cond\"><sec typ=\"note\">마그넷 프리즌</sec>으로 <sec typ=\"note\">잔해</sec> 중첩을 소모하면</sec>, 2라운드 동안 상기 효과가 추가로 적용됩니다.\n<sec typ=\"cond\">라운드 개시 시</sec> <sec typ=\"cond\"><sec typ=\"note\">잔해</sec>를 보유하지 않은 경우</sec>, 자신의 <sec typ=\"buff\"><buff typ=\"AP_UP\" /> AP <val idx=\"7\" /></sec>이(가) 증가합니다."}